{
  "announcement": {
    "enabled": true,
    "title": "Временные неполадки",
    "message": "Мессенджер недоступен, выполняется перенос данных"
  },
  "services": {
    "auth":           { "label": "Авторизация",          "status": "warn",   "text": "Ограничено"   },
    "messaging":      { "label": "Отправка сообщений",   "status": "down", "text": "Отключено" },
    "channels":       { "label": "Создание каналов",     "status": "down",   "text": "Отключено"   },
    "chats":          { "label": "Создание чатов",       "status": "down",   "text": "Отключено"   },
    "search":         { "label": "Поиск",                "status": "down",   "text": "Отключено"   },
    "change_profile": { "label": "Изменение профиля",    "status": "down", "text": "Отключено" }
  }
}
